neutron_policy_server/__init__.py
neutron_policy_server/wsgi.py
neutron_policy_server/tests/__init__.py
neutron_policy_server/tests/test.py
neutron_policy_server/tests/test_neutron_address_pair.py
neutron_policy_server-0.1.0.data/scripts/neutron-policy-server-wsgi
neutron_policy_server-0.1.0.dist-info/AUTHORS
neutron_policy_server-0.1.0.dist-info/METADATA
neutron_policy_server-0.1.0.dist-info/WHEEL
neutron_policy_server-0.1.0.dist-info/entry_points.txt
neutron_policy_server-0.1.0.dist-info/pbr.json
neutron_policy_server-0.1.0.dist-info/top_level.txt
neutron_policy_server-0.1.0.dist-info/RECORD
