Metadata-Version: 2.1
Name: neutron-policy-server
Version: 0.1.0
Summary: Advanced policy server for Neutron
Home-page: https://vexxhost.github.io/neutron-policy-server/
Author: VEXXHOST, Inc.
Author-email: support@vexxhost.com
License: UNKNOWN
Project-URL: Bug Tracker, https://github.com/vexxhost/neutron-policy-server/issues
Project-URL: Documentation, https://vexxhost.github.io/neutron-policy-server/
Project-URL: Source Code, https://github.com/vexxhost/neutron-policy-server
Platform: UNKNOWN
Classifier: Development Status :: 5 - Production/Stable
Classifier: Environment :: OpenStack
Classifier: Intended Audience :: Information Technology
Classifier: Intended Audience :: System Administrators
Classifier: License :: OSI Approved :: Apache Software License
Classifier: Operating System :: POSIX :: Linux
Classifier: Programming Language :: Python
Classifier: Programming Language :: Python :: 3
Classifier: Programming Language :: Python :: 3.10
Classifier: Programming Language :: Python :: 3.11
Classifier: Programming Language :: Python :: 3 :: Only
Classifier: Programming Language :: Python :: Implementation :: CPython
Requires-Python: >=3.8
Requires-Dist: Flask
Requires-Dist: neutron
Requires-Dist: neutron-lib
